asynchronet/__init__.py
asynchronet/dispatcher.py
asynchronet/exceptions.py
asynchronet/logger.py
asynchronet/vendors/__init__.py
asynchronet/vendors/alcatel/__init__.py
asynchronet/vendors/alcatel/alcatel_aos.py
asynchronet/vendors/arista/__init__.py
asynchronet/vendors/arista/arista_eos.py
asynchronet/vendors/aruba/__init__.py
asynchronet/vendors/aruba/aruba_aos_6.py
asynchronet/vendors/aruba/aruba_aos_8.py
asynchronet/vendors/autodetect.py
asynchronet/vendors/base.py
asynchronet/vendors/cisco/__init__.py
asynchronet/vendors/cisco/cisco_asa.py
asynchronet/vendors/cisco/cisco_ios.py
asynchronet/vendors/cisco/cisco_iosxr.py
asynchronet/vendors/cisco/cisco_nxos.py
asynchronet/vendors/cisco/cisco_sg3xx.py
asynchronet/vendors/comware_like.py
asynchronet/vendors/fujitsu/__init__.py
asynchronet/vendors/fujitsu/fujitsu_switch.py
asynchronet/vendors/hp/__init__.py
asynchronet/vendors/hp/hp_comware.py
asynchronet/vendors/hp/hp_comware_limited.py
asynchronet/vendors/huawei/__init__.py
asynchronet/vendors/huawei/huawei.py
asynchronet/vendors/infotecs/HW1000.py
asynchronet/vendors/infotecs/__init__.py
asynchronet/vendors/ios_like.py
asynchronet/vendors/juniper/__init__.py
asynchronet/vendors/juniper/juniper_junos.py
asynchronet/vendors/junos_like.py
asynchronet/vendors/mikrotik/__init__.py
asynchronet/vendors/mikrotik/mikrotik_routeros.py
asynchronet/vendors/terminal/__init__.py
asynchronet/vendors/terminal/terminal.py
asynchronet/vendors/ubiquiti/__init__.py
asynchronet/vendors/ubiquiti/ubiquity_edge.py
asynchronet/version.py
asynchronet-0.1.0.dist-info/LICENSE
asynchronet-0.1.0.dist-info/WHEEL
asynchronet-0.1.0.dist-info/METADATA
asynchronet-0.1.0.dist-info/RECORD
