Metadata-Version: 2.1
Name: asynchronet
Version: 0.1.0
Summary: Fork of netdev: Asynchronous multi-vendor library for interacting with network devices
Home-page: https://netdev.readthedocs.io
License: Apache-2.0
Keywords: netdev,network,netmiko,asyncio
Author: Sergey Yakovlev
Author-email: selfuryon@gmail.com
Requires-Python: >=3.10,<4.0
Classifier: Development Status :: 1 - Beta
Classifier: Framework :: AsyncIO
Classifier: Intended Audience :: Developers
Classifier: Intended Audience :: System Administrators
Classifier: Intended Audience :: Telecommunications Industry
Classifier: License :: OSI Approved :: Apache Software License
Classifier: Programming Language :: Python :: 3
Classifier: Programming Language :: Python :: 3.10
Classifier: Programming Language :: Python :: 3.9
Classifier: Topic :: System :: Networking
Classifier: Topic :: System :: Systems Administration
Provides-Extra: docs
Requires-Dist: Sphinx (>=5.1.1,<6.0.0); extra == "docs"
Requires-Dist: asyncssh (>=2.11.0,<3.0.0)
Requires-Dist: sphinx-rtd-theme (>=1.0.0,<2.0.0); extra == "docs"
Project-URL: Documentation, https://netdev.readthedocs.io
Project-URL: Repository, https://github.com/selfuryon/netdev
